xe_temp/__init__.py
xe_temp/main.py
xe_temp-0.1.0.dist-info/METADATA
xe_temp-0.1.0.dist-info/WHEEL
xe_temp-0.1.0.dist-info/RECORD
